astrolight/__init__.py
astrolight/__main__.py
astrolight/account_connector.py
astrolight/app.py
astrolight/config.py
astrolight/ewelink_connector.py
astrolight/timer.py
astrolight/times/__init__.py
astrolight/times/dynamic_time.py
astrolight/times/expression.py
astrolight/times/sun_time.py
astrolight-0.3.dist-info/METADATA
astrolight-0.3.dist-info/WHEEL
astrolight-0.3.dist-info/entry_points.txt
astrolight-0.3.dist-info/top_level.txt
astrolight-0.3.dist-info/RECORD
